hotpp/__init__.py
hotpp/calibrate.py
hotpp/common.py
hotpp/embed.py
hotpp/eval_downstream.py
hotpp/evaluate.py
hotpp/evaluate_multiseed.py
hotpp/fields.py
hotpp/info.py
hotpp/measure_rps.py
hotpp/parse_wandb_hopt.py
hotpp/train.py
hotpp/train_multiseed.py
hotpp/data/__init__.py
hotpp/data/dataset.py
hotpp/data/module.py
hotpp/data/padded_batch.py
hotpp/losses/__init__.py
hotpp/losses/common.py
hotpp/losses/detection.py
hotpp/losses/diffusion.py
hotpp/losses/next_item.py
hotpp/losses/next_k.py
hotpp/losses/nhp.py
hotpp/losses/rmtpp.py
hotpp/losses/tpp.py
hotpp/losses/hypro/__init__.py
hotpp/losses/hypro/bce.py
hotpp/metrics/__init__.py
hotpp/metrics/horizon.py
hotpp/metrics/horizon_binary_targets.py
hotpp/metrics/next_item.py
hotpp/metrics/otd.py
hotpp/metrics/tmap.py
hotpp/modules/__init__.py
hotpp/modules/base_module.py
hotpp/modules/history_density.py
hotpp/modules/hypro.py
hotpp/modules/most_popular.py
hotpp/modules/next_item.py
hotpp/modules/next_k.py
hotpp/modules/recent_history.py
hotpp/nn/__init__.py
hotpp/nn/aggregator.py
hotpp/nn/denoiser/__init__.py
hotpp/nn/denoiser/gru_denoiser.py
hotpp/nn/denoiser/transformer_denoiser.py
hotpp/nn/encoder/__init__.py
hotpp/nn/encoder/base_encoder.py
hotpp/nn/encoder/embedder.py
hotpp/nn/encoder/encoder.py
hotpp/nn/encoder/rnn_encoder.py
hotpp/nn/encoder/transformer_encoder.py
hotpp/nn/encoder/window.py
hotpp/nn/encoder/rnn/__init__.py
hotpp/nn/encoder/rnn/ctlstm.py
hotpp/nn/encoder/rnn/ode.py
hotpp/nn/encoder/rnn/simple.py
hotpp/nn/encoder/transformer/__init__.py
hotpp/nn/encoder/transformer/attnhp.py
hotpp/nn/encoder/transformer/hf_model.py
hotpp/nn/encoder/transformer/rope.py
hotpp/nn/encoder/transformer/simple.py
hotpp/nn/encoder/transformer/state.py
hotpp/nn/head/__init__.py
hotpp/nn/head/conditional.py
hotpp/nn/head/fc.py
hotpp/utils/__init__.py
hotpp/utils/config.py
hotpp/utils/torch.py
hotpp_benchmark-0.6.5.dist-info/licenses/LICENSE
hotpp_benchmark-0.6.5.dist-info/METADATA
hotpp_benchmark-0.6.5.dist-info/WHEEL
hotpp_benchmark-0.6.5.dist-info/top_level.txt
hotpp_benchmark-0.6.5.dist-info/RECORD
