Metadata-Version: 2.4
Name: hotpp-benchmark
Version: 0.6.5
Summary: Evaluate generative event sequence models on the long horizon prediction task.
Author: Ivan Karpukhin
Author-email: karpuhini@yandex.ru
Classifier: Programming Language :: Python :: 3
Classifier: License :: OSI Approved :: Apache Software License
Classifier: Operating System :: OS Independent
Requires-Python: >=3.9
License-File: LICENSE
Requires-Dist: datasets
Requires-Dist: hydra-core>=1.1.2
Requires-Dist: lightgbm
Requires-Dist: numpy>=1.23
Requires-Dist: pyarrow>=14.0.0
Requires-Dist: pymonad
Requires-Dist: pyspark>=3
Requires-Dist: pytorch-lifestream>=0.6.0
Requires-Dist: pytorch-lightning
Requires-Dist: scikit-learn>=1.3.2
Requires-Dist: scipy>=1.11
Requires-Dist: torch-linear-assignment
Requires-Dist: tqdm
Dynamic: author
Dynamic: author-email
Dynamic: classifier
Dynamic: description
Dynamic: description-content-type
Dynamic: license-file
Dynamic: requires-dist
Dynamic: requires-python
Dynamic: summary
